bobsled_sdk/BobsledException.py
bobsled_sdk/MainClass.py
bobsled_sdk/__init__.py
bobsled_sdk/utils.py
bobsled_python_sdk-1.0.6.dist-info/LICENSE
bobsled_python_sdk-1.0.6.dist-info/METADATA
bobsled_python_sdk-1.0.6.dist-info/WHEEL
bobsled_python_sdk-1.0.6.dist-info/top_level.txt
bobsled_python_sdk-1.0.6.dist-info/RECORD
