Metadata-Version: 2.1
Name: bobsled-python-sdk
Version: 1.0.6
Summary: Python SDK for Bobsled
Author-email: Danny Yu <danny-yu@berkeley.edu>
License: MIT License        
Project-URL: Homepage, https://github.com/bobsled-inc/python-sdk
Project-URL: Bug Tracker, https://github.com/bobsled-inc/python-sdk/issues
Classifier: Programming Language :: Python :: 3
Classifier: License :: OSI Approved :: MIT License
Classifier: Operating System :: OS Independent
Requires-Python: >=3.7
License-File: LICENSE
Requires-Dist: requests
